sinch/__init__.py
sinch/core/__init__.py
sinch/core/adapters/__init__.py
sinch/core/adapters/httpx_adapter.py
sinch/core/adapters/requests_http_transport.py
sinch/core/clients/__init__.py
sinch/core/clients/sinch_client_async.py
sinch/core/clients/sinch_client_base.py
sinch/core/clients/sinch_client_configuration.py
sinch/core/clients/sinch_client_sync.py
sinch/core/deserializers.py
sinch/core/endpoint.py
sinch/core/enums.py
sinch/core/exceptions.py
sinch/core/models/__init__.py
sinch/core/models/base_model.py
sinch/core/models/http_request.py
sinch/core/models/http_response.py
sinch/core/pagination.py
sinch/core/ports/__init__.py
sinch/core/ports/http_transport.py
sinch/core/signature.py
sinch/core/token_manager.py
sinch/domains/__init__.py
sinch/domains/authentication/__init__.py
sinch/domains/authentication/endpoints/__init__.py
sinch/domains/authentication/endpoints/oauth.py
sinch/domains/authentication/exceptions.py
sinch/domains/authentication/models/__init__.py
sinch/domains/authentication/models/authentication.py
sinch/domains/conversation/__init__.py
sinch/domains/conversation/endpoints/__init__.py
sinch/domains/conversation/endpoints/app/__init__.py
sinch/domains/conversation/endpoints/app/create_app.py
sinch/domains/conversation/endpoints/app/delete_app.py
sinch/domains/conversation/endpoints/app/get_app.py
sinch/domains/conversation/endpoints/app/list_apps.py
sinch/domains/conversation/endpoints/app/update_app.py
sinch/domains/conversation/endpoints/capability.py
sinch/domains/conversation/endpoints/contact/__init__.py
sinch/domains/conversation/endpoints/contact/create_contact.py
sinch/domains/conversation/endpoints/contact/delete_contact.py
sinch/domains/conversation/endpoints/contact/get_channel_profile.py
sinch/domains/conversation/endpoints/contact/get_contact.py
sinch/domains/conversation/endpoints/contact/list_contact.py
sinch/domains/conversation/endpoints/contact/merge_contacts.py
sinch/domains/conversation/endpoints/contact/update_contact.py
sinch-1.1.4.dist-info/METADATA
sinch-1.1.4.dist-info/WHEEL
sinch-1.1.4.dist-info/licenses/LICENSE
sinch-1.1.4.dist-info/RECORD
