Metadata-Version: 2.4
Name: sinch
Version: 1.1.4
Summary: Sinch SDK for Python programming language
License: Apache 2.0
License-File: LICENSE
Keywords: sinch,sdk
Author: Sinch Developer Experience Team
Author-email: devexp@sinch.com
Requires-Python: >=3.9
Classifier: Intended Audience :: Developers
Classifier: License :: OSI Approved :: Apache Software License
Classifier: License :: Other/Proprietary License
Classifier: Operating System :: OS Independent
Classifier: Programming Language :: Python
Classifier: Programming Language :: Python :: 3
Classifier: Programming Language :: Python :: 3.9
Classifier: Programming Language :: Python :: 3.10
Classifier: Programming Language :: Python :: 3.11
Classifier: Programming Language :: Python :: 3.12
Classifier: Programming Language :: Python :: 3.13
Classifier: Programming Language :: Python :: 3.14
Classifier: Programming Language :: Python :: Implementation :: CPython
Classifier: Topic :: Communications :: Telephony
Classifier: Topic :: Software Development :: Libraries :: Python Modules
Requires-Dist: httpx
Requires-Dist: requests
Project-URL: Documentation, https://developers.sinch.com
Project-URL: Repository, https://github.com/sinch/sinch-sdk-python
